setup.py
notypebuiltins/__init__.py
notypebuiltins/loader.py
notypebuiltins.egg-info/PKG-INFO
notypebuiltins.egg-info/SOURCES.txt
notypebuiltins.egg-info/dependency_links.txt
notypebuiltins.egg-info/top_level.txt